<?xml version="1.0" encoding="utf-8"?>
<resources>

    <string-array name="net_is_off">
        <item>请连网体验更多功能</item>
    </string-array>

    <string-array name="net_connecting">
        <item>正在连接网络</item>
    </string-array>

    <string-array name="net_connected">
        <item>网络已连接</item>
    </string-array>

    <string-array name="net_disconnected">
        <item>网络已断开</item>
    </string-array>

    <string-array name="login_server_success">
        <item>登录成功，快来陪我玩</item>
    </string-array>

    <string-array name="no_audio_input">
        <item>我没听见哪！</item>
        <item>你怎么不说话！</item>
        <item>你能大点声吗？</item>
        <item>我没听清楚！</item>
    </string-array>

    <string-array name="no_net_use">
        <item>貌似网络不太好啊</item>
        <item>这网速！慢的跟蜗牛一样呀</item>
        <item>当前网络状况不佳，休息一会儿吧</item>
        <item>网络开小差了！</item>
    </string-array>

</resources>
